convertlib/__init__.py
convertlib/convertlib.py
convertlib-0.0.1.3.dist-info/LICENSE
convertlib-0.0.1.3.dist-info/METADATA
convertlib-0.0.1.3.dist-info/WHEEL
convertlib-0.0.1.3.dist-info/top_level.txt
convertlib-0.0.1.3.dist-info/RECORD
