Metadata-Version: 2.1
Name: convertlib
Version: 0.0.1.3
Summary: Converte arquivos
Home-page: https://github.com/hectorsalg/convertlib
Author: Hector Salgueiros e Lizzandro
Author-email: hectorsalg@ufpi.edu.br
Requires-Python: >=3.8
License-File: LICENSE
Requires-Dist: convertapi
